MatricesM/__init__.py
MatricesM/exampleMatrices.py
MatricesM/matrix.py
MatricesM/C_funcs/constructors.c
MatricesM/C_funcs/constructors.cp36-win_amd64.pyd
MatricesM/C_funcs/linalg.cp36-win_amd64.pyd
MatricesM/C_funcs/linalg.pyx
MatricesM/C_funcs/randgen.cp36-win_amd64.pyd
MatricesM/C_funcs/randgen.pyx
MatricesM/C_funcs/zerone.c
MatricesM/C_funcs/zerone.cp36-win_amd64.pyd
MatricesM/constructors/__init__.py
MatricesM/constructors/matrices.py
MatricesM/customs/__init__.py
MatricesM/customs/funcs.py
MatricesM/customs/objects.py
MatricesM/errors/__init__.py
MatricesM/errors/errors.py
MatricesM/filter/__init__.py
MatricesM/filter/apply.py
MatricesM/filter/combine.py
MatricesM/filter/find.py
MatricesM/filter/grouping.py
MatricesM/filter/match.py
MatricesM/filter/replace.py
MatricesM/filter/sample.py
MatricesM/filter/where.py
MatricesM/linalg/LU.py
MatricesM/linalg/QR.py
MatricesM/linalg/SVD.py
MatricesM/linalg/__init__.py
MatricesM/linalg/adjoint.py
MatricesM/linalg/eigen.py
MatricesM/linalg/inverse.py
MatricesM/linalg/minor.py
MatricesM/linalg/nilpotency.py
MatricesM/linalg/perma.py
MatricesM/linalg/rrechelon.py
MatricesM/linalg/symmetry.py
MatricesM/linalg/transpose.py
MatricesM/matrixops/__init__.py
MatricesM/matrixops/add.py
MatricesM/matrixops/arithmetic.py
MatricesM/matrixops/bitwise.py
MatricesM/matrixops/comparison.py
MatricesM/matrixops/concat.py
MatricesM/matrixops/getsetdel.py
MatricesM/matrixops/joins.py
MatricesM/matrixops/matdelDim.py
MatricesM/matrixops/remove.py
MatricesM/matrixops/repr.py
MatricesM/matrixops/rounding.py
MatricesM/setup/__init__.py
MatricesM/setup/argpro.py
MatricesM/setup/declare.py
MatricesM/setup/fileops.py
MatricesM/setup/listify.py
MatricesM/setup/matfill.py
MatricesM/setup/stringfy.py
MatricesM/stats/__init__.py
MatricesM/stats/corr.py
MatricesM/stats/cov.py
MatricesM/stats/describe.py
MatricesM/stats/freq.py
MatricesM/stats/iqr.py
MatricesM/stats/mean.py
MatricesM/stats/median.py
MatricesM/stats/minmax.py
MatricesM/stats/mode.py
MatricesM-0.9a24.post2.dist-info/LICENSE.txt
MatricesM-0.9a24.post2.dist-info/METADATA
MatricesM-0.9a24.post2.dist-info/WHEEL
MatricesM-0.9a24.post2.dist-info/top_level.txt
MatricesM-0.9a24.post2.dist-info/RECORD
