Metadata-Version: 2.1
Name: MatricesM
Version: 0.9a24.post2
Summary: Python>=3.6 library for creating and using matrices used in linear algebra and statistics
Home-page: https://github.com/MathStuff/Matrices
Author: semihM
Author-email: 
License: MIT
Keywords: matrix,matrices,dataframe,linear algebra,statistics,mathematics
Platform: UNKNOWN
Classifier: Programming Language :: Python :: 3.6
Classifier: Programming Language :: Python :: 3.7
Classifier: Programming Language :: Python :: 3.8
Classifier: Development Status :: 3 - Alpha
Classifier: License :: OSI Approved :: MIT License
Classifier: Natural Language :: English
Classifier: Operating System :: OS Independent
Classifier: Topic :: Scientific/Engineering :: Mathematics
Requires-Python: >=3.6
